french_opendata_complete_mcp.py
ign_geo_services.py
iflow_mcp_nikoko107_mcp_datagouv_ign-0.1.1.dist-info/METADATA
iflow_mcp_nikoko107_mcp_datagouv_ign-0.1.1.dist-info/WHEEL
iflow_mcp_nikoko107_mcp_datagouv_ign-0.1.1.dist-info/entry_points.txt
iflow_mcp_nikoko107_mcp_datagouv_ign-0.1.1.dist-info/top_level.txt
iflow_mcp_nikoko107_mcp_datagouv_ign-0.1.1.dist-info/RECORD
