Metadata-Version: 2.4
Name: iflow-mcp-nikoko107-mcp-datagouv-ign
Version: 0.1.1
Summary: Serveur MCP complet pour data.gouv.fr + 4 APIs nationales françaises
Author: nikoko107
Requires-Python: >=3.8
Requires-Dist: mcp>=1.0.0
Requires-Dist: httpx>=0.27.0
Dynamic: requires-python
